slack_webhook/__init__.py
slack_webhook/block_kit.py
slack_webhook/slack.py
slack_webhook_alpa-0.0.6.dist-info/LICENSE
slack_webhook_alpa-0.0.6.dist-info/METADATA
slack_webhook_alpa-0.0.6.dist-info/WHEEL
slack_webhook_alpa-0.0.6.dist-info/top_level.txt
slack_webhook_alpa-0.0.6.dist-info/RECORD
