Metadata-Version: 2.1
Name: slack-webhook-alpa
Version: 0.0.6
Summary: Wrapper for slack_sdk
Home-page: https://github.com/alpaalpa/slack-webhook
Author: Albert Pang
Author-email: alpaaccount@mac.com
License: UNKNOWN
Platform: UNKNOWN
Classifier: Programming Language :: Python :: 3
Classifier: License :: OSI Approved :: MIT License
Classifier: Operating System :: OS Independent
Requires-Python: >=3.8
Requires-Dist: requests
